mokei/__init__.py
mokei/_middlewares.py
mokei/client.py
mokei/config.py
mokei/datatypes.py
mokei/exceptions.py
mokei/logging.py
mokei/middlewares.py
mokei/mokei.py
mokei/request.py
mokei/response.py
mokei/serializer.py
mokei/websocket.py
mokei/wsclient.py
mokei/js/mokei.js
mokei-0.2.18.dist-info/METADATA
mokei-0.2.18.dist-info/WHEEL
mokei-0.2.18.dist-info/licenses/LICENSE
mokei-0.2.18.dist-info/RECORD
