Metadata-Version: 2.4
Name: mokei
Version: 0.2.18
Summary: A simple asynchronous Python web framework built on aiohttp.
Project-URL: Homepage, https://github.com/deuxglaces/mokei
Project-URL: Issues, https://github.com/deuxglaces/mokei/issues
Author-email: deuxglaces <dev@deuxglaces.com>
License-File: LICENSE
Classifier: License :: OSI Approved :: MIT License
Classifier: Operating System :: OS Independent
Classifier: Programming Language :: Python :: 3
Requires-Python: >=3.10
Requires-Dist: aiohttp-asgi>=0.5.2
Requires-Dist: aiohttp-jinja2>=1.6
Requires-Dist: aiohttp-swagger>=1.0.16
Requires-Dist: aiohttp>=3.9.5
Requires-Dist: aiosignal>=1.3.1
Requires-Dist: async-timeout>=4.0.3
Requires-Dist: attrs>=23.1.0
Requires-Dist: charset-normalizer>=3.3.2
Requires-Dist: frozenlist>=1.4.0
Requires-Dist: idna>=3.4
Requires-Dist: jinja2>=3.1.2
Requires-Dist: markupsafe>=2.1.3
Requires-Dist: multidict>=6.0.4
Requires-Dist: pydantic>=2.10.6
Requires-Dist: pyyaml>=6.0.1
Requires-Dist: yarl>=1.9.3
